feature/__init__.py
feature/feature/__init__.py
feature/feature/feature.py
feature/feature/sensor.py
feature/feature/sensor_document.py
feature/featureCluster/__init__.py
feature/featureCluster/feature_cluster.py
feature/featureCluster/position.py
feature/featureCluster/position_document.py
featureMetadataFetcher/__init__.py
featureMetadataFetcher/feature_metadata_fetcher.py
featureMetadataFetcher/sensor_metadata_fetcher.py
utils/__init__.py
utils/feature_util.py
aicns_feature_metadata-0.0.2.dist-info/LICENSE
aicns_feature_metadata-0.0.2.dist-info/METADATA
aicns_feature_metadata-0.0.2.dist-info/WHEEL
aicns_feature_metadata-0.0.2.dist-info/top_level.txt
aicns_feature_metadata-0.0.2.dist-info/RECORD
